data3_network_agent/__init__.py
data3_network_agent/lib.py
data3_network_agent-0.0.5.dist-info/METADATA
data3_network_agent-0.0.5.dist-info/WHEEL
data3_network_agent-0.0.5.dist-info/top_level.txt
data3_network_agent-0.0.5.dist-info/RECORD
